{
 "updated": "2026-07-14",
 "events": [
  {
   "symbol": "LEG",
   "name": "LEGGETT & PLATT INC  (LEG)  (CIK 0000058492)",
   "event_type": "outside_date",
   "event_date": "2028-04-13",
   "filed": "2026-07-09",
   "source": "DEFM14A 0000058492-26-000364",
   "source_url": "https://www.sec.gov/Archives/edgar/data/58492/000005849226000364/legdefm14a.htm",
   "notes": "regex-extracted from primary doc; full read required before any trade"
  },
  {
   "symbol": "OGN",
   "name": "Organon & Co.  (OGN)  (CIK 0001821825)",
   "event_type": "merger_vote",
   "event_date": "2026-07-23",
   "filed": "2026-06-17",
   "source": "DEFM14A 0001193125-26-273323",
   "source_url": "https://www.sec.gov/Archives/edgar/data/1821825/000119312526273323/d15298ddefm14a.htm",
   "notes": "regex-extracted from primary doc; full read required before any trade"
  },
  {
   "symbol": "OGN",
   "name": "Organon & Co.  (OGN)  (CIK 0001821825)",
   "event_type": "outside_date",
   "event_date": "2027-04-26",
   "filed": "2026-06-17",
   "source": "DEFM14A 0001193125-26-273323",
   "source_url": "https://www.sec.gov/Archives/edgar/data/1821825/000119312526273323/d15298ddefm14a.htm",
   "notes": "regex-extracted from primary doc; full read required before any trade"
  },
  {
   "symbol": "LPSN",
   "name": "LIVEPERSON INC  (LPSN)  (CIK 0001102993)",
   "event_type": "merger_vote",
   "event_date": "2026-08-20",
   "filed": "2026-07-09",
   "source": "DEFM14A 0001213900-26-076759",
   "source_url": "https://www.sec.gov/Archives/edgar/data/1102993/000121390026076759/ea0297465-01.htm",
   "notes": "regex-extracted from primary doc; full read required before any trade"
  },
  {
   "symbol": "LPSN",
   "name": "LIVEPERSON INC  (LPSN)  (CIK 0001102993)",
   "event_type": "outside_date",
   "event_date": "2026-12-05",
   "filed": "2026-07-09",
   "source": "DEFM14A 0001213900-26-076759",
   "source_url": "https://www.sec.gov/Archives/edgar/data/1102993/000121390026076759/ea0297465-01.htm",
   "notes": "regex-extracted from primary doc; full read required before any trade"
  },
  {
   "symbol": "RAMP",
   "name": "LiveRamp Holdings, Inc.  (RAMP)  (CIK 0000733269)",
   "event_type": "merger_vote",
   "event_date": "2026-08-17",
   "filed": "2026-07-06",
   "source": "DEFM14A 0001104659-26-080505",
   "source_url": "https://www.sec.gov/Archives/edgar/data/733269/000110465926080505/tm264528-7_defm14aseq1.htm",
   "notes": "regex-extracted from primary doc; full read required before any trade"
  },
  {
   "symbol": "EQH",
   "name": "Equitable Holdings, Inc.  (EQH, EQH-PA, EQH-PC)  (CIK 0001333986)",
   "event_type": "merger_vote",
   "event_date": "2026-07-30",
   "filed": "2026-06-23",
   "source": "DEFM14A 0001193125-26-279668",
   "source_url": "https://www.sec.gov/Archives/edgar/data/1333986/000119312526279668/d115497ddefm14a.htm",
   "notes": "regex-extracted from primary doc; full read required before any trade"
  },
  {
   "symbol": "EQH",
   "name": "Equitable Holdings, Inc.  (EQH, EQH-PA, EQH-PC)  (CIK 0001333986)",
   "event_type": "outside_date",
   "event_date": "2026-12-26",
   "filed": "2026-06-23",
   "source": "DEFM14A 0001193125-26-279668",
   "source_url": "https://www.sec.gov/Archives/edgar/data/1333986/000119312526279668/d115497ddefm14a.htm",
   "notes": "regex-extracted from primary doc; full read required before any trade"
  },
  {
   "symbol": "CRBG",
   "name": "Corebridge Financial, Inc.  (CRBD, CRBG)  (CIK 0001889539)",
   "event_type": "merger_vote",
   "event_date": "2026-07-30",
   "filed": "2026-06-23",
   "source": "DEFM14A 0001193125-26-279656",
   "source_url": "https://www.sec.gov/Archives/edgar/data/1889539/000119312526279656/d115497ddefm14a.htm",
   "notes": "regex-extracted from primary doc; full read required before any trade | SYMBOL CORRECTED 2026-07-13: regex extracted CRBD; broker tape confirms Corebridge trades as CRBG (journal, session 9)"
  },
  {
   "symbol": "CRBG",
   "name": "Corebridge Financial, Inc.  (CRBD, CRBG)  (CIK 0001889539)",
   "event_type": "outside_date",
   "event_date": "2026-12-26",
   "filed": "2026-06-23",
   "source": "DEFM14A 0001193125-26-279656",
   "source_url": "https://www.sec.gov/Archives/edgar/data/1889539/000119312526279656/d115497ddefm14a.htm",
   "notes": "regex-extracted from primary doc; full read required before any trade | SYMBOL CORRECTED 2026-07-13: regex extracted CRBD; broker tape confirms Corebridge trades as CRBG (journal, session 9)"
  },
  {
   "symbol": "MDV",
   "name": "MODIV INDUSTRIAL, INC.  (MDV, MDV-PA)  (CIK 0001645873)",
   "event_type": "merger_vote",
   "event_date": "2026-08-10",
   "filed": "2026-06-24",
   "source": "DEFM14A 0001104659-26-077331",
   "source_url": "https://www.sec.gov/Archives/edgar/data/1645873/000110465926077331/tm2615734-8_defm14a.htm",
   "notes": "regex-extracted from primary doc; full read required before any trade"
  },
  {
   "symbol": "AMRX",
   "name": "Amneal Pharmaceuticals, Inc.  (AMRX)  (CIK 0001723128)",
   "event_type": "outside_date",
   "event_date": "2026-11-17",
   "filed": "2026-06-29",
   "source": "DEFM14A 0001140361-26-026611",
   "source_url": "https://www.sec.gov/Archives/edgar/data/1723128/000114036126026611/ny20075452x2_defm14a.htm",
   "notes": "regex-extracted from primary doc; full read required before any trade"
  },
  {
   "symbol": "GBTG",
   "name": "Global Business Travel Group, Inc.  (GBTG)  (CIK 0001820872)",
   "event_type": "outside_date",
   "event_date": "2026-11-02",
   "filed": "2026-07-06",
   "source": "DEFM14A 0001140361-26-027649",
   "source_url": "https://www.sec.gov/Archives/edgar/data/1820872/000114036126027649/ny20072693x2_defm14a.htm",
   "notes": "regex-extracted from primary doc; full read required before any trade"
  },
  {
   "symbol": "IPCX",
   "name": "Inflection Point Acquisition Corp. III  (IPCX, IPCXR, IPCXU)  (CIK 0002012318)",
   "event_type": "merger_vote",
   "event_date": "2026-07-28",
   "filed": "2026-07-08",
   "source": "DEFM14A 0001213900-26-076450",
   "source_url": "https://www.sec.gov/Archives/edgar/data/2012318/000121390026076450/ea0297441-01.htm",
   "notes": "regex-extracted from primary doc; full read required before any trade"
  },
  {
   "symbol": "AXTA",
   "name": "Axalta Coating Systems Ltd.  (AXTA)  (CIK 0001616862)",
   "event_type": "merger_vote",
   "event_date": "2026-08-05",
   "filed": "2026-06-24",
   "source": "DEFM14A 0001193125-26-280277",
   "source_url": "https://www.sec.gov/Archives/edgar/data/1616862/000119312526280277/d107826ddefm14a.htm",
   "notes": "regex-extracted from primary doc; full read required before any trade"
  },
  {
   "symbol": "AVB",
   "event_type": "merger_vote",
   "event_date": "2026-08-12",
   "source_url": "https://www.sec.gov/Archives/edgar/data/915912/000110465926083113/tm2619865-1_defm14a.htm",
   "source": "DEFM14A 0001104659-26-083113 filed 2026-07-13 (CIK 915912, AvalonBay; ticker via EDGAR submissions API)",
   "note": "mega-cap REIT; specialist-covered; spread territory, not kink-screen supply"
  },
  {
   "symbol": "APGE",
   "event_type": "merger_vote",
   "event_date": "2026-08-11",
   "source_url": "https://www.sec.gov/Archives/edgar/data/1974640/000114036126028341/ny20076262x2_defm14a.htm",
   "source": "DEFM14A 0001140361-26-028341 filed 2026-07-13 (CIK 1974640, Apogee Therapeutics; ticker via EDGAR submissions API)",
   "note": "personal position exists in account (blind-spot disclosure); merger votes never feed long options per playbook"
  },
  {
   "symbol": "HUN",
   "event_type": "outside_date",
   "event_date": "2027-09-15",
   "source_url": "https://www.sec.gov/Archives/edgar/data/1307954/000119312526302130/d149884ddefm14a.htm",
   "source": "DEFM14A 0001193125-26-302130 filed 2026-07-13 (CIK 1307954, Huntsman; ticker via EDGAR submissions API)",
   "note": "extracted meeting_date 2026-07-09 FAILED plausibility (pre-dates filing), dropped; outside date kept"
  },
  {
   "symbol": "AGEN",
   "event_type": "debt_maturity",
   "event_date": "2026-11-26",
   "source_url": "https://www.sec.gov/Archives/edgar/data/1098972/000095017024131263/agen-20241126.htm",
   "source": "8-K 2024-11-27 (accession 0000950170-24-131263): Ocean 1181 LLC promissory note, 2-year term from 2024-11-26, $22M principal ($24.75M per 7/13/26 PIPE SPA sec. 5.14), 12-13% w/ half interest paid in stock, secured by Berkeley mfg facility + Vacaville land",
   "note": "PIPE 7/13/26 obligates only 'commercially reasonable efforts' to extend. Chain exists but event-interval marks self-inconsistent (kink UNRELIABLE 7/16) + gate-5 fail; recheck chain readability as date nears"
  },
  {
   "symbol": "CSTL",
   "name": "Castle Biosciences, Inc. (CSTL)",
   "event_type": "itc_337_institution_due",
   "event_date": "2026-08-14",
   "filed": "2026-07-15",
   "source": "FR docket 3921 (complaint rcvd 7/9, notice pub 7/15)",
   "source_url": "https://www.federalregister.gov/documents/2026/07/15",
   "notes": "complainant vs SkylineDx/Qiagen; institution ~30d after complaint; FD target ~late 2027; track, do not trade yet"
  },
  {
   "symbol": "SEER",
   "name": "Seer, Inc. (SEER)",
   "event_type": "itc_337_target_date_pending",
   "event_date": "2026-08-31",
   "filed": "2026-07-02",
   "source": "FR 337-TA-1508 institution (complaint 5/28, instituted 7/2)",
   "source_url": "https://www.federalregister.gov/documents/2026/07/02",
   "notes": "complainant; target date gets set ~45d after institution - recheck for the scheduling order, then deposit the real FD date"
  },
  {
   "symbol": "INMD",
   "name": "InMode Ltd. (INMD) - RESPONDENT",
   "event_type": "itc_337_institution_due",
   "event_date": "2026-07-27",
   "filed": "2026-06-25",
   "source": "FR docket 3918 (Serendia complaint rcvd 6/22, notice pub 6/25)",
   "source_url": "https://www.federalregister.gov/documents/2026/06/25",
   "notes": "RF-microneedling exclusion would hit core product; optionable mid-cap; institution decision ~30d; the one pipeline name where the RESPONDENT side is the material tradable"
  }
 ]
}